MANIFEST.in
README.md
setup.py
pycacher/__init__.py
pycacher/backends.py
pycacher/batcher.py
pycacher/cacher.py
pycacher/decorators.py
pycacher/utils.py
pycacher.egg-info/PKG-INFO
pycacher.egg-info/SOURCES.txt
pycacher.egg-info/dependency_links.txt
pycacher.egg-info/requires.txt
pycacher.egg-info/top_level.txt