Metadata-Version: 1.0
Name: pycacher
Version: 0.0.2
Summary: pycacher is a python module which enables easy caching layer via function decorators, batcher, etc.
Home-page: http://pycacher.readthedocs.org
Author: Garindra Prahandono
Author-email: garindraprahandono@gmail.com
License: UNKNOWN
Download-URL: http://cloud.github.com/downloads/garindra/pycacher/pycacher-0.0.2.tar.gz
Platform: UNKNOWN
Classifier: Development Status :: 3 - Alpha
Classifier: Environment :: Console
Classifier: Intended Audience :: Developers
Classifier: License :: OSI Approved :: MIT License
Classifier: Operating System :: OS Independent
Classifier: Programming Language :: Python
